smithy_python/__init__.py
smithy_python/_private/__init__.py
smithy_python/_private/abnf.py
smithy_python/_private/api_key_auth.py
smithy_python/_private/auth.py
smithy_python/_private/http/__init__.py
smithy_python/_private/http/aiohttp_client.py
smithy_python/_private/http/crt.py
smithy_python/_private/identity.py
smithy_python/_private/retries/__init__.py
smithy_python/async_utils.py
smithy_python/exceptions.py
smithy_python/httputils.py
smithy_python/interfaces/__init__.py
smithy_python/interfaces/auth.py
smithy_python/interfaces/blobs.py
smithy_python/interfaces/http.py
smithy_python/interfaces/identity.py
smithy_python/interfaces/interceptor.py
smithy_python/interfaces/retries.py
smithy_python/mediatypes.py
smithy_python/protocolutils.py
smithy_python/py.typed
smithy_python/types.py
smithy_python/utils.py
smithy_dafny_standard_library/__init__.py
smithy_dafny_standard_library/internaldafny/extern/ConcurrentCall.py
smithy_dafny_standard_library/internaldafny/extern/DafnyLibraries.py
smithy_dafny_standard_library/internaldafny/extern/OsLang.py
smithy_dafny_standard_library/internaldafny/extern/SortedSets.py
smithy_dafny_standard_library/internaldafny/extern/Time.py
smithy_dafny_standard_library/internaldafny/extern/UTF8.py
smithy_dafny_standard_library/internaldafny/extern/UUID.py
smithy_dafny_standard_library/internaldafny/extern/__init__.py
smithy_dafny_standard_library/internaldafny/generated/Actions.py
smithy_dafny_standard_library/internaldafny/generated/Base64.py
smithy_dafny_standard_library/internaldafny/generated/Base64Lemmas.py
smithy_dafny_standard_library/internaldafny/generated/BoundedInts.py
smithy_dafny_standard_library/internaldafny/generated/ConcurrentCall.py
smithy_dafny_standard_library/internaldafny/generated/DafnyLibraries.py
smithy_dafny_standard_library/internaldafny/generated/DivInternals.py
smithy_dafny_standard_library/internaldafny/generated/DivInternalsNonlinear.py
smithy_dafny_standard_library/internaldafny/generated/DivMod.py
aws_cryptography_internal_standard_library-1.11.1.dist-info/METADATA
aws_cryptography_internal_standard_library-1.11.1.dist-info/WHEEL
aws_cryptography_internal_standard_library-1.11.1.dist-info/RECORD
